panthera/__init__.py
panthera/anharmonicity.py
panthera/cli.py
panthera/displacements.py
panthera/io.py
panthera/nmrelaxation.py
panthera/panther.py
panthera/pes.py
panthera/plotting.py
panthera/pylintrc
panthera/thermochemistry.py
panthera/vibrations.py
panthera-0.5.2.dist-info/LICENSE.rst
panthera-0.5.2.dist-info/WHEEL
panthera-0.5.2.dist-info/METADATA
panthera-0.5.2.dist-info/RECORD
