Metadata-Version: 2.1
Name: panthera
Version: 0.5.2
Summary: Package for calculating thermochemistry with anharmonic corrections
Home-page: https://github.com/lmmentel/panthera
License: MIT
Keywords: vibrations,anharmonic,thermochemistry,chemistry,physics
Author: Lukasz Mentel
Author-email: lmmentel@gmail.com
Maintainer: Lukasz Mentel
Maintainer-email: lmmentel@gmail.com
Requires-Python: >=3.8,<3.10
Classifier: License :: OSI Approved :: MIT License
Classifier: Programming Language :: Python :: 3
Classifier: Programming Language :: Python :: 3.8
Classifier: Programming Language :: Python :: 3.9
Requires-Dist: ase (>=3.22.0,<4.0.0)
Requires-Dist: bmatrix (>=1.0.1,<2.0.0)
Requires-Dist: lxml (>=4.6.3,<5.0.0)
Requires-Dist: matplotlib (>=3.4.3,<4.0.0)
Requires-Dist: numpy (>=1.21.1,<2.0.0)
Requires-Dist: numpydoc (>=1.1.0,<2.0.0)
Requires-Dist: pandas (>=1.3.1,<2.0.0)
Requires-Dist: scipy (>=1.7.1,<2.0.0)
Project-URL: Repository, https://github.com/lmmentel/panthera
